range_dictionary/__init__.py
range_dictionary/errors.py
range_dictionary/range.py
range_dictionary/rangedict.py
RangeDictionary-1.0.2.dist-info/LICENSE.md
RangeDictionary-1.0.2.dist-info/METADATA
RangeDictionary-1.0.2.dist-info/WHEEL
RangeDictionary-1.0.2.dist-info/top_level.txt
RangeDictionary-1.0.2.dist-info/RECORD
