Metadata-Version: 2.1
Name: RangeDictionary
Version: 1.0.2
Summary: Range and RangeDict classes.
Home-page: https://github.com/DallogFheir/range-dictionary
Author: DallogFheir
Author-email: dallog.fheir@gmail.com
License: MIT
License-File: LICENSE.md
